{"nodes": [{"name": "IL1B"}, {"name": "CXCL2"}, {"name": "CXCL3"}, {"name": "JUNB"}, {"name": "IL6"}, {"name": "NFKBIZ"}, {"name": "PTGS2"}], "edges": [{"source": "CXCL2", "target": "CXCL3"}, {"source": "NFKBIZ", "target": "JUNB"}, {"source": "CXCL2", "target": "IL6"}, {"source": "CXCL3", "target": "JUNB"}, {"source": "IL1B", "target": "NFKBIZ"}, {"source": "IL1B", "target": "CXCL3"}, {"source": "PTGS2", "target": "IL1B"}, {"source": "CXCL2", "target": "JUNB"}, {"source": "PTGS2", "target": "CXCL3"}, {"source": "IL6", "target": "NFKBIZ"}, {"source": "PTGS2", "target": "IL6"}, {"source": "CXCL2", "target": "NFKBIZ"}, {"source": "IL6", "target": "CXCL3"}, {"source": "IL1B", "target": "JUNB"}, {"source": "NFKBIZ", "target": "CXCL3"}, {"source": "PTGS2", "target": "CXCL2"}, {"source": "IL1B", "target": "IL6"}, {"source": "PTGS2", "target": "JUNB"}, {"source": "PTGS2", "target": "NFKBIZ"}, {"source": "IL6", "target": "JUNB"}, {"source": "CXCL2", "target": "IL1B"}]}