{"nodes": [{"name": "ZNF142"}, {"name": "KDM6B"}, {"name": "SYNGAP1"}, {"name": "MBD6"}, {"name": "SRCAP"}, {"name": "MNT"}], "edges": [{"source": "MNT", "target": "MBD6"}, {"source": "SRCAP", "target": "KDM6B"}, {"source": "MNT", "target": "ZNF142"}, {"source": "SRCAP", "target": "MBD6"}, {"source": "SRCAP", "target": "ZNF142"}, {"source": "ZNF142", "target": "KDM6B"}, {"source": "MNT", "target": "KDM6B"}, {"source": "MBD6", "target": "SYNGAP1"}, {"source": "KDM6B", "target": "SYNGAP1"}, {"source": "SRCAP", "target": "SYNGAP1"}, {"source": "KDM6B", "target": "MBD6"}, {"source": "ZNF142", "target": "SYNGAP1"}, {"source": "MNT", "target": "SRCAP"}, {"source": "ZNF142", "target": "MBD6"}, {"source": "MNT", "target": "SYNGAP1"}]}