{"nodes": [{"name": "ALDH9A1"}, {"name": "PCYT2"}, {"name": "NIT2"}, {"name": "NIT1"}, {"name": "RBKS"}], "edges": [{"source": "NIT2", "target": "ALDH9A1"}, {"source": "NIT2", "target": "RBKS"}, {"source": "NIT2", "target": "NIT1"}, {"source": "NIT1", "target": "RBKS"}, {"source": "NIT1", "target": "PCYT2"}, {"source": "ALDH9A1", "target": "NIT1"}, {"source": "ALDH9A1", "target": "PCYT2"}, {"source": "RBKS", "target": "PCYT2"}, {"source": "NIT2", "target": "PCYT2"}, {"source": "ALDH9A1", "target": "RBKS"}]}