{"nodes": [{"name": "MFN2"}, {"name": "TOMM70"}, {"name": "VDAC3"}, {"name": "ATAD1"}, {"name": "FUNDC1"}], "edges": [{"source": "FUNDC1", "target": "MFN2"}, {"source": "FUNDC1", "target": "VDAC3"}, {"source": "VDAC3", "target": "ATAD1"}, {"source": "FUNDC1", "target": "ATAD1"}, {"source": "MFN2", "target": "ATAD1"}, {"source": "MFN2", "target": "TOMM70"}, {"source": "ATAD1", "target": "TOMM70"}, {"source": "VDAC3", "target": "TOMM70"}, {"source": "FUNDC1", "target": "TOMM70"}, {"source": "VDAC3", "target": "MFN2"}]}