{"nodes": [{"name": "SERPINH1"}, {"name": "P3H4"}, {"name": "CRTAP"}, {"name": "FKBP10"}, {"name": "P3H1"}, {"name": "FKBP14"}, {"name": "GPX7"}, {"name": "IKBIP"}, {"name": "FKBP9"}, {"name": "FKBP7"}, {"name": "POGLUT2"}], "edges": [{"source": "FKBP14", "target": "CRTAP"}, {"source": "GPX7", "target": "SERPINH1"}, {"source": "FKBP14", "target": "IKBIP"}, {"source": "FKBP7", "target": "SERPINH1"}, {"source": "GPX7", "target": "P3H4"}, {"source": "GPX7", "target": "POGLUT2"}, {"source": "FKBP14", "target": "SERPINH1"}, {"source": "SERPINH1", "target": "CRTAP"}, {"source": "SERPINH1", "target": "IKBIP"}, {"source": "P3H1", "target": "FKBP9"}, {"source": "FKBP7", "target": "P3H4"}, {"source": "FKBP7", "target": "POGLUT2"}, {"source": "FKBP7", "target": "GPX7"}, {"source": "FKBP14", "target": "P3H4"}, {"source": "IKBIP", "target": "CRTAP"}, {"source": "FKBP14", "target": "POGLUT2"}, {"source": "FKBP14", "target": "GPX7"}, {"source": "P3H4", "target": "FKBP10"}, {"source": "P3H4", "target": "CRTAP"}, {"source": "P3H1", "target": "P3H4"}, {"source": "POGLUT2", "target": "CRTAP"}, {"source": "P3H1", "target": "POGLUT2"}, {"source": "POGLUT2", "target": "IKBIP"}, {"source": "GPX7", "target": "P3H1"}, {"source": "GPX7", "target": "FKBP10"}, {"source": "GPX7", "target": "CRTAP"}, {"source": "FKBP10", "target": "CRTAP"}, {"source": "FKBP10", "target": "IKBIP"}, {"source": "FKBP7", "target": "P3H1"}, {"source": "FKBP7", "target": "FKBP10"}, {"source": "POGLUT2", "target": "SERPINH1"}, {"source": "FKBP14", "target": "P3H1"}, {"source": "FKBP7", "target": "FKBP14"}, {"source": "FKBP14", "target": "FKBP10"}, {"source": "FKBP7", "target": "FKBP9"}, {"source": "FKBP10", "target": "SERPINH1"}, {"source": "FKBP14", "target": "FKBP9"}, {"source": "FKBP9", "target": "P3H4"}, {"source": "POGLUT2", "target": "P3H4"}, {"source": "FKBP9", "target": "POGLUT2"}, {"source": "P3H1", "target": "FKBP10"}, {"source": "P3H1", "target": "CRTAP"}, {"source": "P3H1", "target": "IKBIP"}, {"source": "P3H1", "target": "SERPINH1"}, {"source": "FKBP9", "target": "FKBP10"}, {"source": "POGLUT2", "target": "FKBP10"}, {"source": "FKBP9", "target": "CRTAP"}, {"source": "FKBP9", "target": "IKBIP"}, {"source": "P3H4", "target": "IKBIP"}, {"source": "GPX7", "target": "FKBP9"}, {"source": "GPX7", "target": "IKBIP"}, {"source": "FKBP9", "target": "SERPINH1"}, {"source": "FKBP7", "target": "CRTAP"}, {"source": "FKBP7", "target": "IKBIP"}, {"source": "P3H4", "target": "SERPINH1"}]}